aas_compliance_tool/__init__.py
aas_compliance_tool/cli.py
aas_compliance_tool/compliance_check_aasx.py
aas_compliance_tool/compliance_check_json.py
aas_compliance_tool/compliance_check_xml.py
aas_compliance_tool/py.typed
aas_compliance_tool/state_manager.py
aas_compliance_tool/schemas/aasJSONSchema.json
aas_compliance_tool/schemas/aasXMLSchema.xsd
aas_compliance_tool-1.0.0.dist-info/LICENSE
aas_compliance_tool-1.0.0.dist-info/METADATA
aas_compliance_tool-1.0.0.dist-info/NOTICE
aas_compliance_tool-1.0.0.dist-info/WHEEL
aas_compliance_tool-1.0.0.dist-info/entry_points.txt
aas_compliance_tool-1.0.0.dist-info/top_level.txt
aas_compliance_tool-1.0.0.dist-info/RECORD
