Metadata-Version: 2.1
Name: aas-compliance-tool
Version: 1.0.0
Summary: AAS compliance checker based on the Eclipse BaSyx Python SDK
Home-page: https://github.com/rwth-iat/aas-compliance-tool
Author: The AAS Compliance Tool authors
Classifier: Programming Language :: Python :: 3
Classifier: License :: OSI Approved :: MIT License
Classifier: Operating System :: OS Independent
Classifier: Development Status :: 5 - Production/Stable
Requires-Python: >=3.8
License-File: LICENSE
License-File: NOTICE
Requires-Dist: pyecma376-2 >=0.2.4
Requires-Dist: basyx-python-sdk >=1.0.0
